min_rss_gen/__init__.py
min_rss_gen/generator.py
min_rss-0.0.1.dist-info/LICENSE
min_rss-0.0.1.dist-info/METADATA
min_rss-0.0.1.dist-info/WHEEL
min_rss-0.0.1.dist-info/top_level.txt
min_rss-0.0.1.dist-info/RECORD
