Metadata-Version: 2.1
Name: min-rss
Version: 0.0.1
Summary: A correct and minimal RSS 2.0 generator.
Home-page: https://github.com/nwalsh1995/min-rss-gen
Author: Nathan Walsh
Author-email: nwalsh1995@gmail.com
License: UNKNOWN
Platform: UNKNOWN
Classifier: Programming Language :: Python :: 3
Classifier: License :: OSI Approved :: MIT License
Classifier: Operating System :: OS Independent
Requires-Python: >=3.6
